dotatime/A1.py
dotatime/A10.py
dotatime/A2.py
dotatime/A3.py
dotatime/A4.py
dotatime/A5.py
dotatime/A6.py
dotatime/A7.py
dotatime/A8.py
dotatime/A9.py
dotatime/__init__.py
dotatime-0.1.dist-info/licenses/LICENSE.txt
dotatime-0.1.dist-info/METADATA
dotatime-0.1.dist-info/WHEEL
dotatime-0.1.dist-info/top_level.txt
dotatime-0.1.dist-info/RECORD
