Metadata-Version: 2.4
Name: dotatime
Version: 0.1
Summary: <Basic desc>
Author: justin
Author-email: justin@dev.org
Classifier: Programming Language :: Python :: 3
Classifier: License :: OSI Approved :: MIT License
Classifier: Operating System :: OS Independent
License-File: LICENSE.txt
Dynamic: author
Dynamic: author-email
Dynamic: classifier
Dynamic: license-file
Dynamic: summary
